anndata_fcs/__init__.py
anndata_fcs/_convert.py
anndata_fcs/_gate.py
anndata_fcs/_plot.py
anndata_fcs/_types.py
anndata_fcs/_version.py
anndata_fcs/py.typed
anndata_fcs-0.1.1.dist-info/licenses/LICENSE
anndata_fcs-0.1.1.dist-info/WHEEL
anndata_fcs-0.1.1.dist-info/METADATA
anndata_fcs-0.1.1.dist-info/RECORD
