Metadata-Version: 2.4
Name: anndata-fcs
Version: 0.1.1
Summary: Converting FCS files to AnnData objects.
Author-email: harryhaller001 <harryhaller001@gmail.com>
Maintainer-email: harryhaller001 <harryhaller001@gmail.com>
Requires-Python: >=3.10
Classifier: Development Status :: 3 - Alpha
Classifier: Intended Audience :: Science/Research
Classifier: License :: OSI Approved :: MIT License
Classifier: Natural Language :: English
Classifier: Operating System :: OS Independent
Classifier: Programming Language :: Python :: 3 :: Only
Classifier: Programming Language :: Python :: 3.10
Classifier: Programming Language :: Python :: 3.11
Classifier: Programming Language :: Python :: 3.12
Classifier: Programming Language :: Python :: 3.13
Classifier: Typing :: Typed
License-File: LICENSE
Requires-Dist: anndata
Requires-Dist: flowio
Requires-Dist: matplotlib
Requires-Dist: ipython ; extra == "docs"
Requires-Dist: nbsphinx ; extra == "docs"
Requires-Dist: sphinx ; extra == "docs"
Requires-Dist: sphinx-autoapi ; extra == "docs"
Requires-Dist: sphinx-autodoc-typehints ; extra == "docs"
Requires-Dist: sphinx-book-theme ; extra == "docs"
Requires-Dist: coverage ; extra == "test"
Requires-Dist: flit ; extra == "test"
Requires-Dist: ipykernel ; extra == "test"
Requires-Dist: ipython ; extra == "test"
Requires-Dist: ipywidgets ; extra == "test"
Requires-Dist: mypy ; extra == "test"
Requires-Dist: pandas-stubs ; extra == "test"
Requires-Dist: pre-commit ; extra == "test"
Requires-Dist: pytest ; extra == "test"
Requires-Dist: ruff ; extra == "test"
Requires-Dist: scanpy ; extra == "test"
Requires-Dist: twine ; extra == "test"
Project-URL: Documentation, https://harryhaller001.github.io/anndata-fcs/
Project-URL: Home-page, https://github.com/harryhaller001/anndata-fcs
Project-URL: Source, https://github.com/harryhaller001/anndata-fcs
Provides-Extra: docs
Provides-Extra: test
